MANIFEST.in
README.rst
setup.py
banana_py/__init__.py
banana_py/urls.py
banana_py/views.py
banana_py.egg-info/PKG-INFO
banana_py.egg-info/SOURCES.txt
banana_py.egg-info/dependency_links.txt
banana_py.egg-info/not-zip-safe
banana_py.egg-info/requires.txt
banana_py.egg-info/top_level.txt
banana_py/templates/banana_py/fail.html
banana_py/templatetags/__init__.py
banana_py/templatetags/banana_tags.py