Metadata-Version: 1.0
Name: banana-py
Version: 0.1.2
Summary: OAuth2 Backend for MailChimp
Home-page: https://github.com/kennethlove/Banana-Py/
Author: Kenneth Love <kenneth@gigantuan.net>, Chris Jones <chris@brack3t.com>
Author-email: kenneth@gigantuan.net
License: BSD
Keywords: django,mailchimp,oauth2
Platform: UNKNOWN
Classifier: Programming Language :: Python
Classifier: Topic :: Software Development :: Libraries :: Python Modules
Classifier: Framework :: Django
Classifier: Environment :: Web Environment
